ursus/__init__.py
ursus/app.py
ursus/auth.py
ursus/extensions.py
ursus/powerdns/__init__.py
ursus/powerdns/models.py
ursus/powerdns/service.py
ursus/powerdns/templates/list_domains.html
ursus/powerdns/views.py
ursus/utils.py
ursus-0.1.1.dist-info/LICENSE
ursus-0.1.1.dist-info/WHEEL
ursus-0.1.1.dist-info/METADATA
ursus-0.1.1.dist-info/RECORD
