Metadata-Version: 2.1
Name: ursus
Version: 0.1.1
Summary: PowerDNS control panel
Home-page: https://git.sr.ht/~whiisker/ursus/
License: BSD-3-Clause
Author: Quark
Author-email: quark@whiisker.net
Requires-Python: >=3.10.0,<4.0.0
Classifier: License :: OSI Approved :: BSD License
Classifier: Programming Language :: Python :: 3
Classifier: Programming Language :: Python :: 3.10
Classifier: Programming Language :: Python :: 3.11
Requires-Dist: quart (>=0.18.3,<0.19.0)
Project-URL: Repository, https://git.sr.ht/~whiisker/ursus/
